data_specification/__init__.py
data_specification/_version.py
data_specification/abstract_memory_region.py
data_specification/config_setup.py
data_specification/constants.py
data_specification/data_specification.cfg
data_specification/data_specification_executor.py
data_specification/data_specification_executor_functions.py
data_specification/data_specification_generator.py
data_specification/exceptions.py
data_specification/memory_region_collection.py
data_specification/memory_region_real.py
data_specification/memory_region_reference.py
data_specification/reference_context.py
data_specification/enums/__init__.py
data_specification/enums/arithemetic_operation.py
data_specification/enums/commands.py
data_specification/enums/condition.py
data_specification/enums/data_type.py
data_specification/enums/logic_operation.py
data_specification/enums/random_number_generator.py
data_specification/spi/__init__.py
data_specification/spi/abstract_executor_functions.py
SpiNNaker_DataSpecification-1!7.0.0a5.dist-info/LICENSE
SpiNNaker_DataSpecification-1!7.0.0a5.dist-info/LICENSE_POLICY.md
SpiNNaker_DataSpecification-1!7.0.0a5.dist-info/METADATA
SpiNNaker_DataSpecification-1!7.0.0a5.dist-info/WHEEL
SpiNNaker_DataSpecification-1!7.0.0a5.dist-info/top_level.txt
SpiNNaker_DataSpecification-1!7.0.0a5.dist-info/zip-safe
SpiNNaker_DataSpecification-1!7.0.0a5.dist-info/RECORD
