Metadata-Version: 2.1
Name: SpiNNaker-DataSpecification
Version: 1!7.0.0a5
Summary: Specification of Memory Images
Home-page: https://github.com/SpiNNakerManchester/DataSpecification
Maintainer: SpiNNakerTeam
Maintainer-email: spinnakerusers@googlegroups.com
License: Apache-2.0
Keywords: spinnaker,data specification model
Classifier: Development Status :: 5 - Production/Stable
Classifier: Intended Audience :: Developers
Classifier: Intended Audience :: Science/Research
Classifier: License :: OSI Approved :: Apache Software License
Classifier: Natural Language :: English
Classifier: Operating System :: POSIX :: Linux
Classifier: Operating System :: Microsoft :: Windows
Classifier: Operating System :: MacOS
Classifier: Programming Language :: Python :: 3
Classifier: Programming Language :: Python :: 3.7
Classifier: Programming Language :: Python :: 3.8
Classifier: Programming Language :: Python :: 3.9
Classifier: Programming Language :: Python :: 3.10
Classifier: Programming Language :: Python :: 3.11
Requires-Python: <4,>=3.7
License-File: LICENSE
License-File: LICENSE_POLICY.md
Requires-Dist: SpiNNMachine (==1!7.0.0-a5)
Provides-Extra: test
Requires-Dist: pytest-cov ; extra == 'test'
